spydlog-1.0.1.dist-info/RECORD
spydlog-1.0.1.dist-info/WHEEL
spydlog-1.0.1.dist-info/METADATA
spydlog-1.0.1.dist-info/licenses/LICENSE
spydlog/_version.py
spydlog/__init__.py
spydlog/spydlog.cpython-39-darwin.so
